tribal/__init__.py
tribal/algorithms/__init__.py
tribal/algorithms/algorithm_input.py
tribal/algorithms/src/__init__.py
tribal/algorithms/src/genieclust/__init__.py
tribal/algorithms/src/genieclust/c_argfuns.pxd
tribal/algorithms/src/genieclust/c_mst.pxd
tribal/algorithms/src/genieclust/genieclustering_mst.cp311-win_amd64.pyd
tribal/algorithms/src/genieclust/genieclustering_mst.cpp
tribal/algorithms/src/genieclust/genieclustering_mst.cpython-311-x86_64-linux-gnu.so
tribal/algorithms/src/genieclust/genieclustering_mst.pyx
tribal/algorithms/src/genieclust_mst_src/__init__.py
tribal/algorithms/src/genieclust_mst_src/c_argfuns.h
tribal/algorithms/src/genieclust_mst_src/c_common.h
tribal/algorithms/src/genieclust_mst_src/c_disjoint_sets.h
tribal/algorithms/src/genieclust_mst_src/c_distance.h
tribal/algorithms/src/genieclust_mst_src/c_mst.h
tribal/algorithms/src/gmknn/__init__.py
tribal/algorithms/src/gmknn/binaries/__init__.py
tribal/algorithms/src/gmknn/binaries/gmknn_bfs.cp310-win_amd64.pyd
tribal/algorithms/src/gmknn/binaries/gmknn_bfs.cp311-win_amd64.pyd
tribal/algorithms/src/gmknn/binaries/gmknn_bfs.cpython-311-x86_64-linux-gnu.so
tribal/algorithms/src/gmknn/binaries/gmknn_connect.cp310-win_amd64.pyd
tribal/algorithms/src/gmknn/binaries/gmknn_connect.cp311-win_amd64.pyd
tribal/algorithms/src/gmknn/binaries/gmknn_connect.cpython-311-x86_64-linux-gnu.so
tribal/algorithms/src/gmknn/binaries/gmknn_lp.cp310-win_amd64.pyd
tribal/algorithms/src/gmknn/binaries/gmknn_lp.cp311-win_amd64.pyd
tribal/algorithms/src/gmknn/binaries/gmknn_lp.cpython-311-x86_64-linux-gnu.so
tribal/algorithms/src/gmknn/binaries/mknn.cp310-win_amd64.pyd
tribal/algorithms/src/gmknn/binaries/mknn.cp311-win_amd64.pyd
tribal/algorithms/src/gmknn/binaries/mknn.cpython-311-x86_64-linux-gnu.so
tribal/algorithms/src/gmknn/source/__init__.py
tribal/algorithms/src/gmknn/source/gmknn_bfs.cpp
tribal/algorithms/src/gmknn/source/gmknn_bfs.pyx
tribal-0.1.7.dist-info/METADATA
tribal-0.1.7.dist-info/WHEEL
tribal-0.1.7.dist-info/top_level.txt
tribal-0.1.7.dist-info/RECORD
tribal-0.1.7.dist-info/licenses/LICENSE
